LICENSE
paradigm_panes/__init__.py
paradigm_panes/generation.py
paradigm_panes/helpers.py
paradigm_panes/manager.py
paradigm_panes/pane_generator.py
paradigm_panes/panes.py
paradigm_panes/running_scenario.txt
paradigm_panes/settings.py
paradigm_panes-0.3.5.dist-info/LICENSE
paradigm_panes-0.3.5.dist-info/WHEEL
paradigm_panes-0.3.5.dist-info/METADATA
paradigm_panes-0.3.5.dist-info/RECORD
