Metadata-Version: 2.1
Name: paradigm-panes
Version: 0.3.5
Summary: Paradigm panes meant to provide layout specification to be reused elsewhere.
Home-page: https://github.com/UAlbertaALTLab/paradigm-panes
License: Apache License v2.0
Keywords: paradigm,panes
Author: Uladzimir Bondarau
Author-email: bondarau@ualberta.ca
Requires-Python: >=3.9,<4.0
Classifier: License :: Other/Proprietary License
Classifier: Programming Language :: Python :: 3
Classifier: Programming Language :: Python :: 3.10
Classifier: Programming Language :: Python :: 3.9
Requires-Dist: hfst-optimized-lookup (>=0.0.13,<0.1.0)
Requires-Dist: more-itertools (>=8.7.0,<8.8.0)
Requires-Dist: pathlib
Requires-Dist: typing-extensions (>=3.7,<4.0)
Project-URL: Repository, https://github.com/UAlbertaALTLab/paradigm-panes
